pypi_datetime/__init__.py
pypi_datetime/roi_time.py
pypi_datetime/time_tools.py
pypi_datetime-0.0.1.dist-info/LICENSE.txt
pypi_datetime-0.0.1.dist-info/METADATA
pypi_datetime-0.0.1.dist-info/WHEEL
pypi_datetime-0.0.1.dist-info/top_level.txt
pypi_datetime-0.0.1.dist-info/RECORD
